gatools/__init__.py
gatools/colors.py
gatools/commons.py
gatools/container.py
gatools/ctxman.py
gatools/decorators.py
gatools/dictkeys.py
gatools/dictops.py
gatools/envs.py
gatools/files.py
gatools/jsonencoder.py
gatools/logger.py
gatools/oar.py
gatools/pyplot.py
gatools/strings.py
gatools/tables.py
gatools/temp.py
gatools/utils.py
python_gatools-0.1.6.dist-info/METADATA
python_gatools-0.1.6.dist-info/WHEEL
python_gatools-0.1.6.dist-info/top_level.txt
python_gatools-0.1.6.dist-info/RECORD
